image_tools/__init__.py
image_tools/filters.py
image_tools/utils.py
image_tools_anderson1985-0.1.0.dist-info/METADATA
image_tools_anderson1985-0.1.0.dist-info/WHEEL
image_tools_anderson1985-0.1.0.dist-info/top_level.txt
image_tools_anderson1985-0.1.0.dist-info/RECORD
