Metadata-Version: 2.4
Name: image_tools_anderson1985
Version: 0.1.0
Summary: Pacote simples de processamento de imagens
Home-page: https://github.com/andersonasnunes/image_tools_andernunes
Author: Anderson Nunes
Author-email: ander_snunes@icloud.com
Classifier: Programming Language :: Python :: 3
Classifier: License :: OSI Approved :: MIT License
Classifier: Operating System :: OS Independent
Requires-Python: >=3.8
Requires-Dist: Pillow>=9.0.0
